enigma_utils.cpython-310-i386-linux-gnu.so
enigma_utils-1.0.0.dist-info/LICENSE
enigma_utils-1.0.0.dist-info/top_level.txt
enigma_utils-1.0.0.dist-info/RECORD
enigma_utils-1.0.0.dist-info/WHEEL
enigma_utils-1.0.0.dist-info/METADATA
enigma_utils.libs/libstdc++-8baf04f9.so.6.0.28
enigma_utils.libs/libgcc_s-8b50eaaa.so.1
